[
  {
    "level": 1,
    "pointRequired": 0,
    "freeItems": [
      {
        "Key": "201_7_1",
        "Value": "1"
      }
    ],
    "vipItems": [
      {
        "Key": "Energy",
        "Value": "100"
      }
    ]
  },
  {
    "level": 2,
    "pointRequired": 50,
    "freeItems": [
      {
        "Key": "2_1_7",
        "Value": "1"
      }
    ],
    "vipItems": [
      {
        "Key": "207_7_1",
        "Value": "1"
      },
      {
        "Key": "209_4_1",
        "Value": "1"
      }
    ]
  },
  {
    "level": 3,
    "pointRequired": 100,
    "freeItems": [
      {
        "Key": "Energy",
        "Value": "50"
      }
    ],
    "vipItems": [
      {
        "Key": "207_7_1",
        "Value": "1"
      }
    ]
  },
  {
    "level": 4,
    "pointRequired": 125,
    "freeItems": [
      {
        "Key": "204_4_2",
        "Value": "1"
      }
    ],
    "vipItems": [
      {
        "Key": "201_7_2",
        "Value": "1"
      },
      {
        "Key": "104_7_1",
        "Value": "1"
      }
    ]
  },
  {
    "level": 5,
    "pointRequired": 150,
    "freeItems": [
      {
        "Key": "5_1_5",
        "Value": "1"
      }
    ],
    "vipItems": [
      {
        "Key": "Gem",
        "Value": "10"
      }
    ]
  },
  {
    "level": 6,
    "pointRequired": 175,
    "freeItems": [
      {
        "Key": "205_7_1",
        "Value": "1"
      }
    ],
    "vipItems": [
      {
        "Key": "107_6_2",
        "Value": "1"
      }
    ]
  },
  {
    "level": 7,
    "pointRequired": 200,
    "freeItems": [
      {
        "Key": "Energy",
        "Value": "25"
      }
    ],
    "vipItems": [
      {
        "Key": "203_7_1",
        "Value": "1"
      }
    ]
  },
  {
    "level": 8,
    "pointRequired": 225,
    "freeItems": [
      {
        "Key": "4_1_1",
        "Value": "1"
      },
      {
        "Key": "104_7_1",
        "Value": "1"
      }
    ],
    "vipItems": [
      {
        "Key": "3_1_5",
        "Value": "1"
      },
      {
        "Key": "2_1_7",
        "Value": "1"
      },
      {
        "Key": "1_1_1",
        "Value": "1"
      }
    ]
  },
  {
    "level": 9,
    "pointRequired": 250,
    "freeItems": [
      {
        "Key": "107_6_2",
        "Value": "1"
      }
    ],
    "vipItems": [
      {
        "Key": "205_7_1",
        "Value": "1"
      },
      {
        "Key": "205_7_2",
        "Value": "1"
      }
    ]
  },
  {
    "level": 10,
    "pointRequired": 275,
    "freeItems": [
      {
        "Key": "6_1_7",
        "Value": "1"
      },
      {
        "Key": "209_4_1",
        "Value": "1"
      }
    ],
    "vipItems": [
      {
        "Key": "5_1_7",
        "Value": "1"
      },
      {
        "Key": "6_1_5",
        "Value": "1"
      },
      {
        "Key": "4_1_1",
        "Value": "1"
      }
    ]
  },
  {
    "level": 11,
    "pointRequired": 300,
    "freeItems": [
      {
        "Key": "201_7_2",
        "Value": "1"
      }
    ],
    "vipItems": [
      {
        "Key": "205_7_1",
        "Value": "1"
      }
    ]
  },
  {
    "level": 12,
    "pointRequired": 325,
    "freeItems": [
      {
        "Key": "3_1_5",
        "Value": "1"
      }
    ],
    "vipItems": [
      {
        "Key": "203_7_2",
        "Value": "1"
      },
      {
        "Key": "209_4_1",
        "Value": "1"
      }
    ]
  },
  {
    "level": 13,
    "pointRequired": 350,
    "freeItems": [
      {
        "Key": "206_4_2",
        "Value": "1"
      }
    ],
    "vipItems": [
      {
        "Key": "207_7_1",
        "Value": "1"
      }
    ]
  },
  {
    "level": 14,
    "pointRequired": 375,
    "freeItems": [
      {
        "Key": "203_7_1",
        "Value": "1"
      }
    ],
    "vipItems": [
      {
        "Key": "201_7_2",
        "Value": "1"
      },
      {
        "Key": "104_7_1",
        "Value": "1"
      }
    ]
  },
  {
    "level": 15,
    "pointRequired": 400,
    "freeItems": [
      {
        "Key": "4_1_1",
        "Value": "1"
      }
    ],
    "vipItems": [
      {
        "Key": "Gem",
        "Value": "15"
      }
    ]
  },
  {
    "level": 16,
    "pointRequired": 425,
    "freeItems": [
      {
        "Key": "205_7_1",
        "Value": "1"
      }
    ],
    "vipItems": [
      {
        "Key": "107_6_2",
        "Value": "1"
      }
    ]
  },
  {
    "level": 17,
    "pointRequired": 450,
    "freeItems": [
      {
        "Key": "Energy",
        "Value": "50"
      }
    ],
    "vipItems": [
      {
        "Key": "203_7_3",
        "Value": "1"
      }
    ]
  },
  {
    "level": 18,
    "pointRequired": 475,
    "freeItems": [
      {
        "Key": "8_1_4",
        "Value": "1"
      }
    ],
    "vipItems": [
      {
        "Key": "9_1_4",
        "Value": "1"
      },
      {
        "Key": "6_1_5",
        "Value": "1"
      },
      {
        "Key": "7_1_1",
        "Value": "1"
      }
    ]
  },
  {
    "level": 19,
    "pointRequired": 500,
    "freeItems": [
      {
        "Key": "107_6_2",
        "Value": "1"
      },
      {
        "Key": "104_7_2",
        "Value": "1"
      }
    ],
    "vipItems": [
      {
        "Key": "205_7_1",
        "Value": "1"
      }
    ]
  },
  {
    "level": 20,
    "pointRequired": 525,
    "freeItems": [
      {
        "Key": "9_1_5",
        "Value": "1"
      }
    ],
    "vipItems": [
      {
        "Key": "11_1_5",
        "Value": "1"
      },
      {
        "Key": "10_1_1",
        "Value": "1"
      }
    ]
  },
  {
    "level": 21,
    "pointRequired": 550,
    "freeItems": [
      {
        "Key": "201_7_2",
        "Value": "1"
      }
    ],
    "vipItems": [
      {
        "Key": "Energy",
        "Value": "100"
      }
    ]
  },
  {
    "level": 22,
    "pointRequired": 575,
    "freeItems": [
      {
        "Key": "10_1_1",
        "Value": "1"
      }
    ],
    "vipItems": [
      {
        "Key": "207_7_1",
        "Value": "1"
      },
      {
        "Key": "209_4_2",
        "Value": "1"
      }
    ]
  },
  {
    "level": 23,
    "pointRequired": 600,
    "freeItems": [
      {
        "Key": "206_4_3",
        "Value": "1"
      }
    ],
    "vipItems": [
      {
        "Key": "207_7_1",
        "Value": "1"
      }
    ]
  },
  {
    "level": 24,
    "pointRequired": 625,
    "freeItems": [
      {
        "Key": "203_7_2",
        "Value": "1"
      }
    ],
    "vipItems": [
      {
        "Key": "201_7_2",
        "Value": "1"
      },
      {
        "Key": "104_7_2",
        "Value": "1"
      }
    ]
  },
  {
    "level": 25,
    "pointRequired": 650,
    "freeItems": [
      {
        "Key": "11_1_5",
        "Value": "1"
      },
      {
        "Key": "209_4_1",
        "Value": "1"
      }
    ],
    "vipItems": [
      {
        "Key": "Gem",
        "Value": "20"
      }
    ]
  },
  {
    "level": 26,
    "pointRequired": 675,
    "freeItems": [
      {
        "Key": "205_7_1",
        "Value": "1"
      }
    ],
    "vipItems": [
      {
        "Key": "107_6_2",
        "Value": "1"
      }
    ]
  },
  {
    "level": 27,
    "pointRequired": 700,
    "freeItems": [
      {
        "Key": "Energy",
        "Value": "75"
      }
    ],
    "vipItems": [
      {
        "Key": "203_7_1",
        "Value": "1"
      }
    ]
  },
  {
    "level": 28,
    "pointRequired": 725,
    "freeItems": [
      {
        "Key": "12_1_1",
        "Value": "1"
      }
    ],
    "vipItems": [
      {
        "Key": "13_1_4",
        "Value": "1"
      },
      {
        "Key": "11_1_5",
        "Value": "1"
      },
      {
        "Key": "12_1_1",
        "Value": "1"
      }
    ]
  },
  {
    "level": 29,
    "pointRequired": 750,
    "freeItems": [
      {
        "Key": "107_6_2",
        "Value": "1"
      }
    ],
    "vipItems": [
      {
        "Key": "205_7_1",
        "Value": "1"
      },
      {
        "Key": "205_7_2",
        "Value": "1"
      }
    ]
  },
  {
    "level": 30,
    "pointRequired": 775,
    "freeItems": [
      {
        "Key": "104_7_3",
        "Value": "1"
      }
    ],
    "vipItems": [
      {
        "Key": "13_1_4",
        "Value": "1"
      }
    ]
  },
  {
    "level": 31,
    "pointRequired": 800,
    "freeItems": [
      {
        "Key": "201_7_2",
        "Value": "1"
      }
    ],
    "vipItems": [
      {
        "Key": "205_7_1",
        "Value": "1"
      }
    ]
  },
  {
    "level": 32,
    "pointRequired": 825,
    "freeItems": [
      {
        "Key": "13_1_4",
        "Value": "1"
      }
    ],
    "vipItems": [
      {
        "Key": "203_7_2",
        "Value": "1"
      },
      {
        "Key": "206_4_4",
        "Value": "1"
      }
    ]
  },
  {
    "level": 33,
    "pointRequired": 850,
    "freeItems": [
      {
        "Key": "206_4_4",
        "Value": "1"
      }
    ],
    "vipItems": [
      {
        "Key": "207_7_1",
        "Value": "1"
      }
    ]
  },
  {
    "level": 34,
    "pointRequired": 875,
    "freeItems": [
      {
        "Key": "203_7_3",
        "Value": "1"
      }
    ],
    "vipItems": [
      {
        "Key": "201_7_2",
        "Value": "1"
      },
      {
        "Key": "104_7_2",
        "Value": "1"
      }
    ]
  },
  {
    "level": 35,
    "pointRequired": 900,
    "freeItems": [
      {
        "Key": "12_1_1",
        "Value": "1"
      }
    ],
    "vipItems": [
      {
        "Key": "Gem",
        "Value": "25"
      }
    ]
  },
  {
    "level": 36,
    "pointRequired": 925,
    "freeItems": [
      {
        "Key": "205_7_1",
        "Value": "1"
      }
    ],
    "vipItems": [
      {
        "Key": "107_6_2",
        "Value": "1"
      }
    ]
  },
  {
    "level": 37,
    "pointRequired": 950,
    "freeItems": [
      {
        "Key": "Energy",
        "Value": "100"
      }
    ],
    "vipItems": [
      {
        "Key": "203_7_3",
        "Value": "1"
      }
    ]
  },
  {
    "level": 38,
    "pointRequired": 975,
    "freeItems": [
      {
        "Key": "16_1_5",
        "Value": "1"
      }
    ],
    "vipItems": [
      {
        "Key": "207_7_1",
        "Value": "1"
      }
    ]
  },
  {
    "level": 39,
    "pointRequired": 1000,
    "freeItems": [
      {
        "Key": "107_6_2",
        "Value": "1"
      }
    ],
    "vipItems": [
      {
        "Key": "205_7_2",
        "Value": "1"
      }
    ]
  },
  {
    "level": 40,
    "pointRequired": 1000,
    "freeItems": [
      {
        "Key": "209_4_2",
        "Value": "1"
      },
      {
        "Key": "209_4_4",
        "Value": "1"
      }
    ],
    "vipItems": [
      {
        "Key": "201_7_2",
        "Value": "1"
      },
      {
        "Key": "205_7_3",
        "Value": "1"
      },
      {
        "Key": "205_7_1",
        "Value": "1"
      }
    ]
  },
  {
    "level": 41,
    "pointRequired": 1000,
    "freeItems": [
      {
        "Key": "Coin",
        "Value": "100"
      }
    ],
    "vipItems": [
      {
        "Key": "Gem",
        "Value": "25"
      }
    ]
  },
  {
    "level": 42,
    "pointRequired": 1000,
    "freeItems": [
      {
        "Key": "Coin",
        "Value": "100"
      }
    ],
    "vipItems": [
      {
        "Key": "Gem",
        "Value": "25"
      }
    ]
  },
  {
    "level": 43,
    "pointRequired": 1000,
    "freeItems": [
      {
        "Key": "Coin",
        "Value": "100"
      }
    ],
    "vipItems": [
      {
        "Key": "Gem",
        "Value": "25"
      }
    ]
  },
  {
    "level": 44,
    "pointRequired": 1000,
    "freeItems": [
      {
        "Key": "Coin",
        "Value": "100"
      }
    ],
    "vipItems": [
      {
        "Key": "Gem",
        "Value": "25"
      }
    ]
  },
  {
    "level": 45,
    "pointRequired": 1000,
    "freeItems": [
      {
        "Key": "Coin",
        "Value": "100"
      }
    ],
    "vipItems": [
      {
        "Key": "Gem",
        "Value": "25"
      }
    ]
  },
  {
    "level": 46,
    "pointRequired": 1000,
    "freeItems": [
      {
        "Key": "Coin",
        "Value": "100"
      }
    ],
    "vipItems": [
      {
        "Key": "Gem",
        "Value": "25"
      }
    ]
  },
  {
    "level": 47,
    "pointRequired": 1000,
    "freeItems": [
      {
        "Key": "Coin",
        "Value": "100"
      }
    ],
    "vipItems": [
      {
        "Key": "Gem",
        "Value": "25"
      }
    ]
  },
  {
    "level": 48,
    "pointRequired": 1000,
    "freeItems": [
      {
        "Key": "Coin",
        "Value": "100"
      }
    ],
    "vipItems": [
      {
        "Key": "Gem",
        "Value": "25"
      }
    ]
  },
  {
    "level": 49,
    "pointRequired": 1000,
    "freeItems": [
      {
        "Key": "Coin",
        "Value": "100"
      }
    ],
    "vipItems": [
      {
        "Key": "Gem",
        "Value": "25"
      }
    ]
  },
  {
    "level": 50,
    "pointRequired": 1000,
    "freeItems": [
      {
        "Key": "Coin",
        "Value": "100"
      }
    ],
    "vipItems": [
      {
        "Key": "Gem",
        "Value": "25"
      }
    ]
  },
  {
    "level": 51,
    "pointRequired": 1000,
    "freeItems": [
      {
        "Key": "Coin",
        "Value": "100"
      }
    ],
    "vipItems": [
      {
        "Key": "Gem",
        "Value": "25"
      }
    ]
  },
  {
    "level": 52,
    "pointRequired": 1000,
    "freeItems": [
      {
        "Key": "Coin",
        "Value": "100"
      }
    ],
    "vipItems": [
      {
        "Key": "Gem",
        "Value": "25"
      }
    ]
  },
  {
    "level": 53,
    "pointRequired": 1000,
    "freeItems": [
      {
        "Key": "Coin",
        "Value": "100"
      }
    ],
    "vipItems": [
      {
        "Key": "Gem",
        "Value": "25"
      }
    ]
  },
  {
    "level": 54,
    "pointRequired": 1000,
    "freeItems": [
      {
        "Key": "Coin",
        "Value": "100"
      }
    ],
    "vipItems": [
      {
        "Key": "Gem",
        "Value": "25"
      }
    ]
  },
  {
    "level": 55,
    "pointRequired": 1000,
    "freeItems": [
      {
        "Key": "Coin",
        "Value": "100"
      }
    ],
    "vipItems": [
      {
        "Key": "Gem",
        "Value": "25"
      }
    ]
  },
  {
    "level": 56,
    "pointRequired": 1000,
    "freeItems": [
      {
        "Key": "Coin",
        "Value": "100"
      }
    ],
    "vipItems": [
      {
        "Key": "Gem",
        "Value": "25"
      }
    ]
  },
  {
    "level": 57,
    "pointRequired": 1000,
    "freeItems": [
      {
        "Key": "Coin",
        "Value": "100"
      }
    ],
    "vipItems": [
      {
        "Key": "Gem",
        "Value": "25"
      }
    ]
  },
  {
    "level": 58,
    "pointRequired": 1000,
    "freeItems": [
      {
        "Key": "Coin",
        "Value": "100"
      }
    ],
    "vipItems": [
      {
        "Key": "Gem",
        "Value": "25"
      }
    ]
  },
  {
    "level": 59,
    "pointRequired": 1000,
    "freeItems": [
      {
        "Key": "Coin",
        "Value": "100"
      }
    ],
    "vipItems": [
      {
        "Key": "Gem",
        "Value": "25"
      }
    ]
  },
  {
    "level": 60,
    "pointRequired": 1000,
    "freeItems": [
      {
        "Key": "Coin",
        "Value": "100"
      }
    ],
    "vipItems": [
      {
        "Key": "Gem",
        "Value": "25"
      }
    ]
  }
]